__init__.py
botik/__init__.py
botik/app.py
botik/api/__init__.py
botik/api/api.py
botik/api/api_type.py
botik/api/send_message.py
botik/input/__init__.py
botik/input/user_input.py
botik/input/keyboard/__init__.py
botik/input/keyboard/keyboard_markup.py
botik/input/keyboard/markup_factory.py
botik/input/keyboard/button/__init__.py
botik/input/keyboard/button/button.py
botik/input/keyboard/button/button_data.py
botik/input/keyboard/button/button_factory.py
botik/input/keyboard/button/button_function.py
botik/input/message_handlers/__init__.py
botik/input/message_handlers/raw_message_handlers.py
botik/input/message_handlers/events/__init__.py
botik/input/message_handlers/events/bot_event.py
botik/input/message_handlers/events/bot_events.py
botik/input/message_handlers/events/contact_share_event.py
botik/input/message_handlers/events/geo_share_event.py
botik/input/message_handlers/events/got_attachment_event.py
botik/navigation/__init__.py
botik/navigation/navigation.py
botik/navigation/routing.py
botik/page/__init__.py
botik/page/input_page.py
botik/page/page.py
botik/page/page_data.py
botik/page/page_factory.py
botik/user/__init__.py
botik/user/storage.py
botik/user/user.py
botik/user/user_base.py
botik-0.0.2.dist-info/LICENSE
botik-0.0.2.dist-info/METADATA
botik-0.0.2.dist-info/WHEEL
botik-0.0.2.dist-info/top_level.txt
botik-0.0.2.dist-info/RECORD
