Metadata-Version: 2.1
Name: botik
Version: 0.0.2
Summary: Botik core package
Author-email: dasstyx <dasstyx@gmail.com>
Project-URL: Documentation, https://botik.readthedocs.io
Project-URL: Homepage, https://github.com/dasstyx/botik
Project-URL: Bug Tracker, https://github.com/dasstyx/botik/issues
Keywords: api,framework,bot,messenger,async,botik
Classifier: Programming Language :: Python :: 3
Classifier: License :: OSI Approved :: MIT License
Classifier: Operating System :: OS Independent
Requires-Python: >=3.7
License-File: LICENSE
Requires-Dist: pillow
